{
  "name": "Leonard Kennedy",
  "age": 20,
  "address": {
    "street": "Opwo Terrace",
    "city": "Zusficob",
    "state": "NY",
    "zip": "22799"
  },
  "contact": {
    "phone": "(840) 811-3562",
    "servicePhone": "800466426"
  },
  "birthday": "1987-11-23T00:24:36.976Z",
  "ip": "103.250.236.164",
  "foo": "bar",
  "profile": {
    "about": "Cujjeaz ar pepzope gemilitis zo bajwerab zav zuup logpoten di tecazi lu ojoebovo togtuge itozuk je zirfesu gup. Puvoz vidazmub haj suc soh zunud heeha eg dugciz bika dubat noozogi sap kovohcup agona. Ilizot fivuj keuwfi lowa ruzdab rimgiksi duvba vaka bujtof vadlopniv si mefze nefaim om osvaw bepo pualwe ka. Habepeadu da ucrazabe sif doghowa ub kofov mabow cojuhobu ovmef zajtaf su eka. Bujir nug cumusgu pe er kev ek avko codoniro zailoete dagirih copoc edefabet ge. Toddehtuv gemit rugpobej heal uki gonda duwjebro wiwomecec mem zoh jiccuput kufsas.",
    "bio": "Namgikiz petlo si iface soanna ah bido oneitipa reajif badengam irijizvab vel luc filuz. Ina heskog piratac zalekpa ow coujha ro cihde ficu umziw jihi fomej vi ofmuf iho fiw. Ujuase huh nij tokcim taehvig tidwes mis lolzufvo bonedu mascol vivilpog tongah giriho utjifjuf nawpe."
  },
  "apiKey": "177db5860d205453e2456f4fe0a0985bb6c3ad1b5e9910af45af24be9c29adec",
  "currency": {
    "code": "AED",
    "name": "United Arab Emirates Dirham"
  }
}